noonlight/__init__.py
noonlight-0.1.1.dist-info/LICENSE
noonlight-0.1.1.dist-info/METADATA
noonlight-0.1.1.dist-info/WHEEL
noonlight-0.1.1.dist-info/top_level.txt
noonlight-0.1.1.dist-info/RECORD
