Metadata-Version: 2.1
Name: noonlight
Version: 0.1.1
Summary: A Python library for interacting with the Noonlight API
Home-page: https://github.com/konnected-io/noonlight-py
Author: Nate Clark, Nick Gordon, Konnected Inc
Author-email: help@konnected.io
License: MIT License
Project-URL: Homepage, https://github.com/konnected-io/noonlight-py
Project-URL: API Documentation, https://docs.noonlight.com
Platform: UNKNOWN
Requires-Dist: aiohttp
